spyxpo/__init__.py
spyxpo/example.py
spyxpo-0.0.1.dist-info/METADATA
spyxpo-0.0.1.dist-info/WHEEL
spyxpo-0.0.1.dist-info/top_level.txt
spyxpo-0.0.1.dist-info/RECORD
