Metadata-Version: 2.1
Name: spyxpo
Version: 0.0.1
Summary: Advance tech at an affordable cost
Author: Spyxpo (Mantresh Khurana)
Author-email: <mantreshkhurana@spyxpo.com>
Keywords: python,spyxpo,ai,ml
Classifier: Development Status :: 1 - Planning
Classifier: Intended Audience :: Developers
Classifier: Programming Language :: Python :: 3
Classifier: Operating System :: Unix
Classifier: Operating System :: MacOS :: MacOS X
Classifier: Operating System :: Microsoft :: Windows
Requires-Dist: numpy
